django_slackin_public/__init__.py
django_slackin_public/conf.py
django_slackin_public/context.py
django_slackin_public/forms.py
django_slackin_public/signals.py
django_slackin_public/slack.py
django_slackin_public/urls.py
django_slackin_public/views.py
django_slackin_public/templates/slackin/base.html
django_slackin_public/templates/slackin/invite/content.html
django_slackin_public/templates/slackin/invite/page.html
django_slackin_public/templates/slackin/invite/styles.html
django_slackin_public-0.1.0.dist-info/DESCRIPTION.rst
django_slackin_public-0.1.0.dist-info/METADATA
django_slackin_public-0.1.0.dist-info/RECORD
django_slackin_public-0.1.0.dist-info/WHEEL
django_slackin_public-0.1.0.dist-info/metadata.json
django_slackin_public-0.1.0.dist-info/top_level.txt
example/__init__.py
example/manage.py
example/settings.py
example/tests.py
example/urls.py
example/wsgi.py
