Metadata-Version: 2.0
Name: django-slackin-public
Version: 0.1.0
Summary: Slack invitation page for Django (like rauchg/slackin)
Home-page: https://github.com/mtlpy/django-slackin-public
Author: Pior Bastida
Author-email: pior@pbastida.net
License: MIT License
Platform: UNKNOWN
Classifier: Environment :: Web Environment
Classifier: Framework :: Django
Classifier: Intended Audience :: Developers
Classifier: License :: OSI Approved :: MIT License
Classifier: Operating System :: OS Independent
Classifier: Programming Language :: Python
Classifier: Programming Language :: Python :: 2
Classifier: Programming Language :: Python :: 3
Classifier: Topic :: Internet :: WWW/HTTP
Classifier: Topic :: Internet :: WWW/HTTP :: Dynamic Content
Requires-Dist: slackclient
